setup.py
infi/__init__.py
infi.dtypes.iqn.egg-info/PKG-INFO
infi.dtypes.iqn.egg-info/SOURCES.txt
infi.dtypes.iqn.egg-info/dependency_links.txt
infi.dtypes.iqn.egg-info/namespace_packages.txt
infi.dtypes.iqn.egg-info/not-zip-safe
infi.dtypes.iqn.egg-info/top_level.txt
infi/dtypes/__init__.py
infi/dtypes/iqn/__init__.py
infi/dtypes/iqn/__version__.py