Metadata-Version: 1.1
Name: infi.dtypes.iqn
Version: 0.2.0
Summary: Datatype for IQN
Home-page: https://github.com/infinidat/infi.dtypes.iqn
Author: Dror Levin
Author-email: drorl@infinidat.com
License: PSF
Platform: UNKNOWN
Classifier: Programming Language :: Python :: 2.7
Classifier: Programming Language :: Python :: 3.4
Classifier: Programming Language :: Python :: 3.5
